ms_mint_app/__init__.py
ms_mint_app/_version.py
ms_mint_app/app.py
ms_mint_app/auth.py
ms_mint_app/database.py
ms_mint_app/filelock.py
ms_mint_app/messages.py
ms_mint_app/plugin_interface.py
ms_mint_app/plugin_manager.py
ms_mint_app/tools.py
ms_mint_app/assets/MINT-logo-header.png
ms_mint_app/assets/dataSorted.js
ms_mint_app/assets/favicon.ico
ms_mint_app/assets/logo.png
ms_mint_app/plugins/__init__.py
ms_mint_app/plugins/analysis.py
ms_mint_app/plugins/metadata.py
ms_mint_app/plugins/ms_files.py
ms_mint_app/plugins/processing.py
ms_mint_app/plugins/quality_control.py
ms_mint_app/plugins/target_optimization.py
ms_mint_app/plugins/targets.py
ms_mint_app/plugins/workspaces.py
ms_mint_app/plugins/analysis_tools/__init__.py
ms_mint_app/plugins/analysis_tools/distributions.py
ms_mint_app/plugins/analysis_tools/heatmap.py
ms_mint_app/plugins/analysis_tools/hierachical_clustering.py
ms_mint_app/plugins/analysis_tools/pca.py
ms_mint_app/plugins/analysis_tools/plotting.py
ms_mint_app/scripts/Mint.py
ms_mint_app/scripts/__init__.py
ms_mint_app/static/Standard_Peaklist.csv
ms_mint_app/static/__init__.py
ms_mint_app/static/logo/logo.ico
ms_mint_app/static/logo/logo.png
ms_mint_app/static/logo/logo.svg
ms_mint_app-1.1.2.dist-info/LICENSE
ms_mint_app-1.1.2.dist-info/METADATA
ms_mint_app-1.1.2.dist-info/WHEEL
ms_mint_app-1.1.2.dist-info/entry_points.txt
ms_mint_app-1.1.2.dist-info/top_level.txt
ms_mint_app-1.1.2.dist-info/RECORD
