Metadata-Version: 2.1
Name: ms-mint-app
Version: 1.1.2
Summary: Metabolomics Integrator Interactive Web-Application (Mint)
Author-email: Soren Wacker <swacker@ucalgary.ca>
Maintainer-email: Soren Wacker <swacker@ucalgary.ca>
License: Version 2.0, January 2004
Project-URL: Homepage, https://github.com/LewisResearchGroup/ms-mint-app
Project-URL: Documentation, https://lewisresearchgroup.github.io/ms-mint-app/
Project-URL: Repository, https://github.com/LewisResearchGroup/ms-mint-app.git
Project-URL: Bug Tracker, https://github.com/LewisResearchGroup/ms-mint-app/issues
Keywords: metabolomics,integrator,mint
Classifier: Programming Language :: Python :: 3
Classifier: Programming Language :: Python :: 3.9
Classifier: Programming Language :: Python :: 3.10
Classifier: Programming Language :: Python :: 3.11
Classifier: Programming Language :: Python :: 3.12
Classifier: License :: OSI Approved :: Apache Software License
Classifier: Operating System :: OS Independent
Requires-Python: >=3.9
License-File: LICENSE
Requires-Dist: ms-mint >=1.1.1
Requires-Dist: xlsxwriter
Requires-Dist: waitress
Requires-Dist: dash
Requires-Dist: dash[diskcache]
Requires-Dist: dash-extensions
Requires-Dist: dash-bootstrap-components
Requires-Dist: flask-login
Requires-Dist: flask-migrate
Requires-Dist: flask-wtf
Requires-Dist: urllib3
Requires-Dist: dash-tabulator
Requires-Dist: dash-uploader ==0.7.0a1
Requires-Dist: beautifulsoup4
Requires-Dist: dask[diskcache]
Requires-Dist: h5py
Requires-Dist: hdf5plugin
Requires-Dist: werkzeug ==3.0.6
Requires-Dist: packaging ==21.3.0
Requires-Dist: email-validator
